<?xml version="1.0" encoding="utf-8"?>
<EntityRelationships xmlns:xsi="http://www.w3.org/2001/XMLSchema-instance">
  <EntityRelationship Name="msiati_deliveryframeworkcontact_msnfp_deliveryfr">
    <EntityRelationshipType>OneToMany</EntityRelationshipType>
    <IsCustomizable>1</IsCustomizable>
    <IntroducedVersion>1.0.0.0</IntroducedVersion>
    <IsHierarchical>0</IsHierarchical>
    <ReferencingEntityName>msiati_deliveryframeworkcontact</ReferencingEntityName>
    <ReferencedEntityName>msnfp_deliveryframework</ReferencedEntityName>
    <CascadeAssign>NoCascade</CascadeAssign>
    <CascadeDelete>RemoveLink</CascadeDelete>
    <CascadeReparent>NoCascade</CascadeReparent>
    <CascadeShare>NoCascade</CascadeShare>
    <CascadeUnshare>NoCascade</CascadeUnshare>
    <CascadeRollupView>NoCascade</CascadeRollupView>
    <IsValidForAdvancedFind>1</IsValidForAdvancedFind>
    <ReferencingAttributeName>msiati_deliveryframeworkid</ReferencingAttributeName>
    <RelationshipDescription>
      <Descriptions>
        <Description description="Unique identifier for Delivery Framework associated with Delivery Framework Contact." languagecode="1033" />
      </Descriptions>
    </RelationshipDescription>
    <EntityRelationshipRoles>
      <EntityRelationshipRole>
        <NavPaneDisplayOption>UseCollectionName</NavPaneDisplayOption>
        <NavPaneArea>Details</NavPaneArea>
        <NavPaneOrder>10000</NavPaneOrder>
        <NavigationPropertyName>msiati_deliveryframeworkid</NavigationPropertyName>
        <RelationshipRoleType>1</RelationshipRoleType>
      </EntityRelationshipRole>
      <EntityRelationshipRole>
        <NavigationPropertyName>msiati_deliveryframeworkcontact_msnfp_deliveryfr</NavigationPropertyName>
        <RelationshipRoleType>0</RelationshipRoleType>
      </EntityRelationshipRole>
    </EntityRelationshipRoles>
  </EntityRelationship>
  <EntityRelationship Name="msiati_msnfp_deliveryframework_msiati_aidtype">
    <EntityRelationshipType>OneToMany</EntityRelationshipType>
    <IsCustomizable>1</IsCustomizable>
    <IntroducedVersion>2.0.0.0</IntroducedVersion>
    <IsHierarchical>0</IsHierarchical>
    <ReferencingEntityName>msiati_aidtype</ReferencingEntityName>
    <ReferencedEntityName>msnfp_deliveryframework</ReferencedEntityName>
    <CascadeAssign>NoCascade</CascadeAssign>
    <CascadeDelete>RemoveLink</CascadeDelete>
    <CascadeReparent>NoCascade</CascadeReparent>
    <CascadeShare>NoCascade</CascadeShare>
    <CascadeUnshare>NoCascade</CascadeUnshare>
    <CascadeRollupView>NoCascade</CascadeRollupView>
    <IsValidForAdvancedFind>1</IsValidForAdvancedFind>
    <ReferencingAttributeName>msiati_deliveryframeworkid</ReferencingAttributeName>
    <RelationshipDescription>
      <Descriptions>
        <Description description="Unique identifier for Delivery Framework associated with Aid Type." languagecode="1033" />
      </Descriptions>
    </RelationshipDescription>
    <EntityRelationshipRoles>
      <EntityRelationshipRole>
        <NavPaneDisplayOption>UseCollectionName</NavPaneDisplayOption>
        <NavPaneArea>Details</NavPaneArea>
        <NavPaneOrder>10000</NavPaneOrder>
        <NavigationPropertyName>msiati_deliveryframeworkid</NavigationPropertyName>
        <RelationshipRoleType>1</RelationshipRoleType>
      </EntityRelationshipRole>
      <EntityRelationshipRole>
        <NavigationPropertyName>msiati_msnfp_deliveryframework_msiati_aidtype</NavigationPropertyName>
        <RelationshipRoleType>0</RelationshipRoleType>
      </EntityRelationshipRole>
    </EntityRelationshipRoles>
  </EntityRelationship>
  <EntityRelationship Name="msiati_msnfp_deliveryframework_msiati_condition">
    <EntityRelationshipType>OneToMany</EntityRelationshipType>
    <IsCustomizable>1</IsCustomizable>
    <IntroducedVersion>1.0.0.0</IntroducedVersion>
    <IsHierarchical>0</IsHierarchical>
    <ReferencingEntityName>msiati_condition</ReferencingEntityName>
    <ReferencedEntityName>msnfp_deliveryframework</ReferencedEntityName>
    <CascadeAssign>NoCascade</CascadeAssign>
    <CascadeDelete>RemoveLink</CascadeDelete>
    <CascadeReparent>NoCascade</CascadeReparent>
    <CascadeShare>NoCascade</CascadeShare>
    <CascadeUnshare>NoCascade</CascadeUnshare>
    <CascadeRollupView>NoCascade</CascadeRollupView>
    <IsValidForAdvancedFind>1</IsValidForAdvancedFind>
    <ReferencingAttributeName>msiati_deliveryframeworkid</ReferencingAttributeName>
    <RelationshipDescription>
      <Descriptions>
        <Description description="Unique identifier for Delivery Framework associated with Condition." languagecode="1033" />
      </Descriptions>
    </RelationshipDescription>
    <EntityRelationshipRoles>
      <EntityRelationshipRole>
        <NavPaneDisplayOption>UseCollectionName</NavPaneDisplayOption>
        <NavPaneArea>Details</NavPaneArea>
        <NavPaneOrder>10000</NavPaneOrder>
        <NavigationPropertyName>msiati_deliveryframeworkid</NavigationPropertyName>
        <RelationshipRoleType>1</RelationshipRoleType>
      </EntityRelationshipRole>
      <EntityRelationshipRole>
        <NavigationPropertyName>msiati_msnfp_deliveryframework_msiati_condition</NavigationPropertyName>
        <RelationshipRoleType>0</RelationshipRoleType>
      </EntityRelationshipRole>
    </EntityRelationshipRoles>
  </EntityRelationship>
  <EntityRelationship Name="msiati_msnfp_deliveryframework_msiati_crsotherfl">
    <EntityRelationshipType>OneToMany</EntityRelationshipType>
    <IsCustomizable>1</IsCustomizable>
    <IntroducedVersion>1.0.0.0</IntroducedVersion>
    <IsHierarchical>0</IsHierarchical>
    <ReferencingEntityName>msiati_crsotherflag</ReferencingEntityName>
    <ReferencedEntityName>msnfp_deliveryframework</ReferencedEntityName>
    <CascadeAssign>NoCascade</CascadeAssign>
    <CascadeDelete>RemoveLink</CascadeDelete>
    <CascadeReparent>NoCascade</CascadeReparent>
    <CascadeShare>NoCascade</CascadeShare>
    <CascadeUnshare>NoCascade</CascadeUnshare>
    <CascadeRollupView>NoCascade</CascadeRollupView>
    <IsValidForAdvancedFind>1</IsValidForAdvancedFind>
    <ReferencingAttributeName>msiati_deliveryframeworkid</ReferencingAttributeName>
    <RelationshipDescription>
      <Descriptions>
        <Description description="Unique identifier for Delivery Framework associated with CRS Other Flag." languagecode="1033" />
      </Descriptions>
    </RelationshipDescription>
    <EntityRelationshipRoles>
      <EntityRelationshipRole>
        <NavPaneDisplayOption>UseCollectionName</NavPaneDisplayOption>
        <NavPaneArea>Details</NavPaneArea>
        <NavPaneOrder>10000</NavPaneOrder>
        <NavigationPropertyName>msiati_deliveryframeworkid</NavigationPropertyName>
        <RelationshipRoleType>1</RelationshipRoleType>
      </EntityRelationshipRole>
      <EntityRelationshipRole>
        <NavigationPropertyName>msiati_msnfp_deliveryframework_msiati_crsotherfl</NavigationPropertyName>
        <RelationshipRoleType>0</RelationshipRoleType>
      </EntityRelationshipRole>
    </EntityRelationshipRoles>
  </EntityRelationship>
  <EntityRelationship Name="msiati_msnfp_deliveryframework_msiati_deliveryfr">
    <EntityRelationshipType>OneToMany</EntityRelationshipType>
    <IsCustomizable>1</IsCustomizable>
    <IntroducedVersion>1.0.0.0</IntroducedVersion>
    <IsHierarchical>0</IsHierarchical>
    <ReferencingEntityName>msiati_deliveryframeworkdescription</ReferencingEntityName>
    <ReferencedEntityName>msnfp_deliveryframework</ReferencedEntityName>
    <CascadeAssign>NoCascade</CascadeAssign>
    <CascadeDelete>RemoveLink</CascadeDelete>
    <CascadeReparent>NoCascade</CascadeReparent>
    <CascadeShare>NoCascade</CascadeShare>
    <CascadeUnshare>NoCascade</CascadeUnshare>
    <CascadeRollupView>NoCascade</CascadeRollupView>
    <IsValidForAdvancedFind>1</IsValidForAdvancedFind>
    <ReferencingAttributeName>msiati_deliveryframeworkid</ReferencingAttributeName>
    <RelationshipDescription>
      <Descriptions>
        <Description description="Unique identifier for Delivery Framework associated with Delivery Framework Description." languagecode="1033" />
      </Descriptions>
    </RelationshipDescription>
    <EntityRelationshipRoles>
      <EntityRelationshipRole>
        <NavPaneDisplayOption>UseCollectionName</NavPaneDisplayOption>
        <NavPaneArea>Details</NavPaneArea>
        <NavPaneOrder>10000</NavPaneOrder>
        <NavigationPropertyName>msiati_deliveryframeworkid</NavigationPropertyName>
        <RelationshipRoleType>1</RelationshipRoleType>
      </EntityRelationshipRole>
      <EntityRelationshipRole>
        <NavigationPropertyName>msiati_msnfp_deliveryframework_msiati_deliveryfr</NavigationPropertyName>
        <RelationshipRoleType>0</RelationshipRoleType>
      </EntityRelationshipRole>
    </EntityRelationshipRoles>
  </EntityRelationship>
  <EntityRelationship Name="msiati_msnfp_deliveryframework_msiati_expenditur">
    <EntityRelationshipType>OneToMany</EntityRelationshipType>
    <IsCustomizable>1</IsCustomizable>
    <IntroducedVersion>1.0.0.0</IntroducedVersion>
    <IsHierarchical>0</IsHierarchical>
    <ReferencingEntityName>msiati_expenditure</ReferencingEntityName>
    <ReferencedEntityName>msnfp_deliveryframework</ReferencedEntityName>
    <CascadeAssign>NoCascade</CascadeAssign>
    <CascadeDelete>RemoveLink</CascadeDelete>
    <CascadeReparent>NoCascade</CascadeReparent>
    <CascadeShare>NoCascade</CascadeShare>
    <CascadeUnshare>NoCascade</CascadeUnshare>
    <CascadeRollupView>NoCascade</CascadeRollupView>
    <IsValidForAdvancedFind>1</IsValidForAdvancedFind>
    <ReferencingAttributeName>msiati_deliveryframeworkid</ReferencingAttributeName>
    <RelationshipDescription>
      <Descriptions>
        <Description description="Unique identifier for Delivery Framework associated with Expenditure." languagecode="1033" />
      </Descriptions>
    </RelationshipDescription>
    <EntityRelationshipRoles>
      <EntityRelationshipRole>
        <NavPaneDisplayOption>UseCollectionName</NavPaneDisplayOption>
        <NavPaneArea>Details</NavPaneArea>
        <NavPaneOrder>10000</NavPaneOrder>
        <NavigationPropertyName>msiati_deliveryframeworkid</NavigationPropertyName>
        <RelationshipRoleType>1</RelationshipRoleType>
      </EntityRelationshipRole>
      <EntityRelationshipRole>
        <NavigationPropertyName>msiati_msnfp_deliveryframework_msiati_expenditur</NavigationPropertyName>
        <RelationshipRoleType>0</RelationshipRoleType>
      </EntityRelationshipRole>
    </EntityRelationshipRoles>
  </EntityRelationship>
  <EntityRelationship Name="msiati_msnfp_deliveryframework_msiati_fssforecas">
    <EntityRelationshipType>OneToMany</EntityRelationshipType>
    <IsCustomizable>1</IsCustomizable>
    <IntroducedVersion>1.0.0.0</IntroducedVersion>
    <IsHierarchical>0</IsHierarchical>
    <ReferencingEntityName>msiati_fssforecast</ReferencingEntityName>
    <ReferencedEntityName>msnfp_deliveryframework</ReferencedEntityName>
    <CascadeAssign>NoCascade</CascadeAssign>
    <CascadeDelete>RemoveLink</CascadeDelete>
    <CascadeReparent>NoCascade</CascadeReparent>
    <CascadeShare>NoCascade</CascadeShare>
    <CascadeUnshare>NoCascade</CascadeUnshare>
    <CascadeRollupView>NoCascade</CascadeRollupView>
    <IsValidForAdvancedFind>1</IsValidForAdvancedFind>
    <ReferencingAttributeName>msiati_deliveryframeworkid</ReferencingAttributeName>
    <RelationshipDescription>
      <Descriptions>
        <Description description="Unique identifier for Delivery Framework associated with FSS Forecast." languagecode="1033" />
      </Descriptions>
    </RelationshipDescription>
    <EntityRelationshipRoles>
      <EntityRelationshipRole>
        <NavPaneDisplayOption>UseCollectionName</NavPaneDisplayOption>
        <NavPaneArea>Details</NavPaneArea>
        <NavPaneOrder>10000</NavPaneOrder>
        <NavigationPropertyName>msiati_deliveryframeworkid</NavigationPropertyName>
        <RelationshipRoleType>1</RelationshipRoleType>
      </EntityRelationshipRole>
      <EntityRelationshipRole>
        <NavigationPropertyName>msiati_msnfp_deliveryframework_msiati_fssforecas</NavigationPropertyName>
        <RelationshipRoleType>0</RelationshipRoleType>
      </EntityRelationshipRole>
    </EntityRelationshipRoles>
  </EntityRelationship>
  <EntityRelationship Name="msiati_msnfp_deliveryframework_msiati_humanitari">
    <EntityRelationshipType>OneToMany</EntityRelationshipType>
    <IsCustomizable>1</IsCustomizable>
    <IntroducedVersion>1.0.0.0</IntroducedVersion>
    <IsHierarchical>0</IsHierarchical>
    <ReferencingEntityName>msiati_humanitarianscope</ReferencingEntityName>
    <ReferencedEntityName>msnfp_deliveryframework</ReferencedEntityName>
    <CascadeAssign>NoCascade</CascadeAssign>
    <CascadeDelete>RemoveLink</CascadeDelete>
    <CascadeReparent>NoCascade</CascadeReparent>
    <CascadeShare>NoCascade</CascadeShare>
    <CascadeUnshare>NoCascade</CascadeUnshare>
    <CascadeRollupView>NoCascade</CascadeRollupView>
    <IsValidForAdvancedFind>1</IsValidForAdvancedFind>
    <ReferencingAttributeName>msiati_deliveryframeworkid</ReferencingAttributeName>
    <RelationshipDescription>
      <Descriptions>
        <Description description="Unique identifier for Delivery Framework associated with Humanitarian Scope." languagecode="1033" />
      </Descriptions>
    </RelationshipDescription>
    <EntityRelationshipRoles>
      <EntityRelationshipRole>
        <NavPaneDisplayOption>UseCollectionName</NavPaneDisplayOption>
        <NavPaneArea>Details</NavPaneArea>
        <NavPaneOrder>10000</NavPaneOrder>
        <NavigationPropertyName>msiati_deliveryframeworkid</NavigationPropertyName>
        <RelationshipRoleType>1</RelationshipRoleType>
      </EntityRelationshipRole>
      <EntityRelationshipRole>
        <NavigationPropertyName>msiati_msnfp_deliveryframework_msiati_humanitari</NavigationPropertyName>
        <RelationshipRoleType>0</RelationshipRoleType>
      </EntityRelationshipRole>
    </EntityRelationshipRoles>
  </EntityRelationship>
  <EntityRelationship Name="msiati_msnfp_deliveryframework_msiati_identifier">
    <EntityRelationshipType>OneToMany</EntityRelationshipType>
    <IsCustomizable>1</IsCustomizable>
    <IntroducedVersion>1.0.0.0</IntroducedVersion>
    <IsHierarchical>0</IsHierarchical>
    <ReferencingEntityName>msiati_identifier</ReferencingEntityName>
    <ReferencedEntityName>msnfp_deliveryframework</ReferencedEntityName>
    <CascadeAssign>NoCascade</CascadeAssign>
    <CascadeDelete>RemoveLink</CascadeDelete>
    <CascadeReparent>NoCascade</CascadeReparent>
    <CascadeShare>NoCascade</CascadeShare>
    <CascadeUnshare>NoCascade</CascadeUnshare>
    <CascadeRollupView>NoCascade</CascadeRollupView>
    <IsValidForAdvancedFind>1</IsValidForAdvancedFind>
    <ReferencingAttributeName>msiati_deliveryframeworkid</ReferencingAttributeName>
    <RelationshipDescription>
      <Descriptions>
        <Description description="Unique identifier for Delivery Framework associated with Identifier." languagecode="1033" />
      </Descriptions>
    </RelationshipDescription>
    <EntityRelationshipRoles>
      <EntityRelationshipRole>
        <NavPaneDisplayOption>UseCollectionName</NavPaneDisplayOption>
        <NavPaneArea>Details</NavPaneArea>
        <NavPaneOrder>10000</NavPaneOrder>
        <NavigationPropertyName>msiati_deliveryframeworkid</NavigationPropertyName>
        <RelationshipRoleType>1</RelationshipRoleType>
      </EntityRelationshipRole>
      <EntityRelationshipRole>
        <NavigationPropertyName>msiati_msnfp_deliveryframework_msiati_identifier</NavigationPropertyName>
        <RelationshipRoleType>0</RelationshipRoleType>
      </EntityRelationshipRole>
    </EntityRelationshipRoles>
  </EntityRelationship>
  <EntityRelationship Name="msiati_msnfp_deliveryframework_msiati_location">
    <EntityRelationshipType>OneToMany</EntityRelationshipType>
    <IsCustomizable>1</IsCustomizable>
    <IntroducedVersion>1.0.0.0</IntroducedVersion>
    <IsHierarchical>0</IsHierarchical>
    <ReferencingEntityName>msiati_location</ReferencingEntityName>
    <ReferencedEntityName>msnfp_deliveryframework</ReferencedEntityName>
    <CascadeAssign>NoCascade</CascadeAssign>
    <CascadeDelete>RemoveLink</CascadeDelete>
    <CascadeReparent>NoCascade</CascadeReparent>
    <CascadeShare>NoCascade</CascadeShare>
    <CascadeUnshare>NoCascade</CascadeUnshare>
    <CascadeRollupView>NoCascade</CascadeRollupView>
    <IsValidForAdvancedFind>1</IsValidForAdvancedFind>
    <ReferencingAttributeName>msiati_deliveryframeworkid</ReferencingAttributeName>
    <RelationshipDescription>
      <Descriptions>
        <Description description="Unique identifier for Delivery Framework associated with Location." languagecode="1033" />
      </Descriptions>
    </RelationshipDescription>
    <EntityRelationshipRoles>
      <EntityRelationshipRole>
        <NavPaneDisplayOption>UseCollectionName</NavPaneDisplayOption>
        <NavPaneArea>Details</NavPaneArea>
        <NavPaneOrder>10000</NavPaneOrder>
        <NavigationPropertyName>msiati_deliveryframeworkid</NavigationPropertyName>
        <RelationshipRoleType>1</RelationshipRoleType>
      </EntityRelationshipRole>
      <EntityRelationshipRole>
        <NavigationPropertyName>msiati_msnfp_deliveryframework_msiati_location</NavigationPropertyName>
        <RelationshipRoleType>0</RelationshipRoleType>
      </EntityRelationshipRole>
    </EntityRelationshipRoles>
  </EntityRelationship>
  <EntityRelationship Name="msiati_msnfp_deliveryframework_msiati_narrativet">
    <EntityRelationshipType>OneToMany</EntityRelationshipType>
    <IsCustomizable>1</IsCustomizable>
    <IntroducedVersion>1.0.0.0</IntroducedVersion>
    <IsHierarchical>0</IsHierarchical>
    <ReferencingEntityName>msiati_narrativetranslation</ReferencingEntityName>
    <ReferencedEntityName>msnfp_deliveryframework</ReferencedEntityName>
    <CascadeAssign>NoCascade</CascadeAssign>
    <CascadeDelete>RemoveLink</CascadeDelete>
    <CascadeReparent>NoCascade</CascadeReparent>
    <CascadeShare>NoCascade</CascadeShare>
    <CascadeUnshare>NoCascade</CascadeUnshare>
    <CascadeRollupView>NoCascade</CascadeRollupView>
    <IsValidForAdvancedFind>1</IsValidForAdvancedFind>
    <ReferencingAttributeName>msiati_deliveryframeworkdid</ReferencingAttributeName>
    <RelationshipDescription>
      <Descriptions>
        <Description description="Unique identifier for Delivery Framework associated with Narrative Translation." languagecode="1033" />
      </Descriptions>
    </RelationshipDescription>
    <EntityRelationshipRoles>
      <EntityRelationshipRole>
        <NavPaneDisplayOption>UseCollectionName</NavPaneDisplayOption>
        <NavPaneArea>Details</NavPaneArea>
        <NavPaneOrder>10000</NavPaneOrder>
        <NavigationPropertyName>msiati_deliveryframeworkdid</NavigationPropertyName>
        <RelationshipRoleType>1</RelationshipRoleType>
      </EntityRelationshipRole>
      <EntityRelationshipRole>
        <NavigationPropertyName>msiati_msnfp_deliveryframework_msiati_narrativet</NavigationPropertyName>
        <RelationshipRoleType>0</RelationshipRoleType>
      </EntityRelationshipRole>
    </EntityRelationshipRoles>
  </EntityRelationship>
  <EntityRelationship Name="msiati_msnfp_deliveryframework_msiati_participat">
    <EntityRelationshipType>OneToMany</EntityRelationshipType>
    <IsCustomizable>1</IsCustomizable>
    <IntroducedVersion>1.0.0.0</IntroducedVersion>
    <IsHierarchical>0</IsHierarchical>
    <ReferencingEntityName>msiati_participatingorganization</ReferencingEntityName>
    <ReferencedEntityName>msnfp_deliveryframework</ReferencedEntityName>
    <CascadeAssign>NoCascade</CascadeAssign>
    <CascadeDelete>RemoveLink</CascadeDelete>
    <CascadeReparent>NoCascade</CascadeReparent>
    <CascadeShare>NoCascade</CascadeShare>
    <CascadeUnshare>NoCascade</CascadeUnshare>
    <CascadeRollupView>NoCascade</CascadeRollupView>
    <IsValidForAdvancedFind>1</IsValidForAdvancedFind>
    <ReferencingAttributeName>msiati_deliveryframeworkid</ReferencingAttributeName>
    <RelationshipDescription>
      <Descriptions>
        <Description description="Unique identifier for Delivery Framework associated with Participating Organization." languagecode="1033" />
      </Descriptions>
    </RelationshipDescription>
    <EntityRelationshipRoles>
      <EntityRelationshipRole>
        <NavPaneDisplayOption>UseCollectionName</NavPaneDisplayOption>
        <NavPaneArea>Details</NavPaneArea>
        <NavPaneOrder>10000</NavPaneOrder>
        <NavigationPropertyName>msiati_deliveryframeworkid</NavigationPropertyName>
        <RelationshipRoleType>1</RelationshipRoleType>
      </EntityRelationshipRole>
      <EntityRelationshipRole>
        <NavigationPropertyName>msiati_msnfp_deliveryframework_msiati_participat</NavigationPropertyName>
        <RelationshipRoleType>0</RelationshipRoleType>
      </EntityRelationshipRole>
    </EntityRelationshipRoles>
  </EntityRelationship>
  <EntityRelationship Name="msiati_msnfp_deliveryframework_msiati_policymark">
    <EntityRelationshipType>OneToMany</EntityRelationshipType>
    <IsCustomizable>1</IsCustomizable>
    <IntroducedVersion>1.0.0.0</IntroducedVersion>
    <IsHierarchical>0</IsHierarchical>
    <ReferencingEntityName>msiati_policymarker</ReferencingEntityName>
    <ReferencedEntityName>msnfp_deliveryframework</ReferencedEntityName>
    <CascadeAssign>NoCascade</CascadeAssign>
    <CascadeDelete>RemoveLink</CascadeDelete>
    <CascadeReparent>NoCascade</CascadeReparent>
    <CascadeShare>NoCascade</CascadeShare>
    <CascadeUnshare>NoCascade</CascadeUnshare>
    <CascadeRollupView>NoCascade</CascadeRollupView>
    <IsValidForAdvancedFind>1</IsValidForAdvancedFind>
    <ReferencingAttributeName>msiati_deliveryframeworkid</ReferencingAttributeName>
    <RelationshipDescription>
      <Descriptions>
        <Description description="Unique identifier for Delivery Framework associated with Policy Marker." languagecode="1033" />
      </Descriptions>
    </RelationshipDescription>
    <EntityRelationshipRoles>
      <EntityRelationshipRole>
        <NavPaneDisplayOption>UseCollectionName</NavPaneDisplayOption>
        <NavPaneArea>Details</NavPaneArea>
        <NavPaneOrder>10000</NavPaneOrder>
        <NavigationPropertyName>msiati_deliveryframeworkid</NavigationPropertyName>
        <RelationshipRoleType>1</RelationshipRoleType>
      </EntityRelationshipRole>
      <EntityRelationshipRole>
        <NavigationPropertyName>msiati_msnfp_deliveryframework_msiati_policymark</NavigationPropertyName>
        <RelationshipRoleType>0</RelationshipRoleType>
      </EntityRelationshipRole>
    </EntityRelationshipRoles>
  </EntityRelationship>
  <EntityRelationship Name="msiati_msnfp_deliveryframework_msiati_recipientc">
    <EntityRelationshipType>OneToMany</EntityRelationshipType>
    <IsCustomizable>1</IsCustomizable>
    <IntroducedVersion>1.0.0.0</IntroducedVersion>
    <IsHierarchical>0</IsHierarchical>
    <ReferencingEntityName>msiati_recipientcountry</ReferencingEntityName>
    <ReferencedEntityName>msnfp_deliveryframework</ReferencedEntityName>
    <CascadeAssign>NoCascade</CascadeAssign>
    <CascadeDelete>RemoveLink</CascadeDelete>
    <CascadeReparent>NoCascade</CascadeReparent>
    <CascadeShare>NoCascade</CascadeShare>
    <CascadeUnshare>NoCascade</CascadeUnshare>
    <CascadeRollupView>NoCascade</CascadeRollupView>
    <IsValidForAdvancedFind>1</IsValidForAdvancedFind>
    <ReferencingAttributeName>msiati_deliveryframeworkid</ReferencingAttributeName>
    <RelationshipDescription>
      <Descriptions>
        <Description description="Unique identifier for Delivery Framework associated with Recipient Country." languagecode="1033" />
      </Descriptions>
    </RelationshipDescription>
    <EntityRelationshipRoles>
      <EntityRelationshipRole>
        <NavPaneDisplayOption>UseCollectionName</NavPaneDisplayOption>
        <NavPaneArea>Details</NavPaneArea>
        <NavPaneOrder>10000</NavPaneOrder>
        <NavigationPropertyName>msiati_deliveryframeworkid</NavigationPropertyName>
        <RelationshipRoleType>1</RelationshipRoleType>
      </EntityRelationshipRole>
      <EntityRelationshipRole>
        <NavigationPropertyName>msiati_msnfp_deliveryframework_msiati_recipientc</NavigationPropertyName>
        <RelationshipRoleType>0</RelationshipRoleType>
      </EntityRelationshipRole>
    </EntityRelationshipRoles>
  </EntityRelationship>
  <EntityRelationship Name="msiati_msnfp_deliveryframework_msiati_recipientr">
    <EntityRelationshipType>OneToMany</EntityRelationshipType>
    <IsCustomizable>1</IsCustomizable>
    <IntroducedVersion>1.0.0.0</IntroducedVersion>
    <IsHierarchical>0</IsHierarchical>
    <ReferencingEntityName>msiati_recipientregion</ReferencingEntityName>
    <ReferencedEntityName>msnfp_deliveryframework</ReferencedEntityName>
    <CascadeAssign>NoCascade</CascadeAssign>
    <CascadeDelete>RemoveLink</CascadeDelete>
    <CascadeReparent>NoCascade</CascadeReparent>
    <CascadeShare>NoCascade</CascadeShare>
    <CascadeUnshare>NoCascade</CascadeUnshare>
    <CascadeRollupView>NoCascade</CascadeRollupView>
    <IsValidForAdvancedFind>1</IsValidForAdvancedFind>
    <ReferencingAttributeName>msiati_deliveryframeworkid</ReferencingAttributeName>
    <RelationshipDescription>
      <Descriptions>
        <Description description="Unique identifier for Delivery Framework associated with Recipient Region." languagecode="1033" />
      </Descriptions>
    </RelationshipDescription>
    <EntityRelationshipRoles>
      <EntityRelationshipRole>
        <NavPaneDisplayOption>UseCollectionName</NavPaneDisplayOption>
        <NavPaneArea>Details</NavPaneArea>
        <NavPaneOrder>10000</NavPaneOrder>
        <NavigationPropertyName>msiati_deliveryframeworkid</NavigationPropertyName>
        <RelationshipRoleType>1</RelationshipRoleType>
      </EntityRelationshipRole>
      <EntityRelationshipRole>
        <NavigationPropertyName>msiati_msnfp_deliveryframework_msiati_recipientr</NavigationPropertyName>
        <RelationshipRoleType>0</RelationshipRoleType>
      </EntityRelationshipRole>
    </EntityRelationshipRoles>
  </EntityRelationship>
  <EntityRelationship Name="msiati_msnfp_deliveryframework_msiati_sector_deliveryframeworkid">
    <EntityRelationshipType>OneToMany</EntityRelationshipType>
    <IsCustomizable>1</IsCustomizable>
    <IntroducedVersion>1.0.0.0</IntroducedVersion>
    <IsHierarchical>0</IsHierarchical>
    <ReferencingEntityName>msiati_sector</ReferencingEntityName>
    <ReferencedEntityName>msnfp_deliveryframework</ReferencedEntityName>
    <CascadeAssign>NoCascade</CascadeAssign>
    <CascadeDelete>RemoveLink</CascadeDelete>
    <CascadeReparent>NoCascade</CascadeReparent>
    <CascadeShare>NoCascade</CascadeShare>
    <CascadeUnshare>NoCascade</CascadeUnshare>
    <CascadeRollupView>NoCascade</CascadeRollupView>
    <IsValidForAdvancedFind>1</IsValidForAdvancedFind>
    <ReferencingAttributeName>msiati_deliveryframeworkid</ReferencingAttributeName>
    <RelationshipDescription>
      <Descriptions>
        <Description description="Unique identifier for Delivery Framework associated with Sector." languagecode="1033" />
      </Descriptions>
    </RelationshipDescription>
    <EntityRelationshipRoles>
      <EntityRelationshipRole>
        <NavPaneDisplayOption>UseCollectionName</NavPaneDisplayOption>
        <NavPaneArea>Details</NavPaneArea>
        <NavPaneOrder>10000</NavPaneOrder>
        <NavigationPropertyName>msiati_deliveryframeworkid</NavigationPropertyName>
        <RelationshipRoleType>1</RelationshipRoleType>
      </EntityRelationshipRole>
      <EntityRelationshipRole>
        <NavigationPropertyName>msiati_msnfp_deliveryframework_msiati_sector_deliveryframeworkid</NavigationPropertyName>
        <RelationshipRoleType>0</RelationshipRoleType>
      </EntityRelationshipRole>
    </EntityRelationshipRoles>
  </EntityRelationship>
  <EntityRelationship Name="msiati_msnfp_deliveryframework_msiati_tag">
    <EntityRelationshipType>OneToMany</EntityRelationshipType>
    <IsCustomizable>1</IsCustomizable>
    <IntroducedVersion>1.0.0.0</IntroducedVersion>
    <IsHierarchical>0</IsHierarchical>
    <ReferencingEntityName>msiati_tag</ReferencingEntityName>
    <ReferencedEntityName>msnfp_deliveryframework</ReferencedEntityName>
    <CascadeAssign>NoCascade</CascadeAssign>
    <CascadeDelete>RemoveLink</CascadeDelete>
    <CascadeReparent>NoCascade</CascadeReparent>
    <CascadeShare>NoCascade</CascadeShare>
    <CascadeUnshare>NoCascade</CascadeUnshare>
    <CascadeRollupView>NoCascade</CascadeRollupView>
    <IsValidForAdvancedFind>1</IsValidForAdvancedFind>
    <ReferencingAttributeName>msiati_deliveryframeworkid</ReferencingAttributeName>
    <RelationshipDescription>
      <Descriptions>
        <Description description="Unique identifier for Delivery Framework associated with Tag." languagecode="1033" />
      </Descriptions>
    </RelationshipDescription>
    <EntityRelationshipRoles>
      <EntityRelationshipRole>
        <NavPaneDisplayOption>UseCollectionName</NavPaneDisplayOption>
        <NavPaneArea>Details</NavPaneArea>
        <NavPaneOrder>10000</NavPaneOrder>
        <NavigationPropertyName>msiati_deliveryframeworkid</NavigationPropertyName>
        <RelationshipRoleType>1</RelationshipRoleType>
      </EntityRelationshipRole>
      <EntityRelationshipRole>
        <NavigationPropertyName>msiati_msnfp_deliveryframework_msiati_tag</NavigationPropertyName>
        <RelationshipRoleType>0</RelationshipRoleType>
      </EntityRelationshipRole>
    </EntityRelationshipRoles>
  </EntityRelationship>
  <EntityRelationship Name="msnfp_deliveryframework_budget_deliveryframeworkid">
    <EntityRelationshipType>OneToMany</EntityRelationshipType>
    <IntroducedVersion>1.0.8</IntroducedVersion>
    <IsHierarchical>0</IsHierarchical>
    <ReferencingEntityName>msnfp_Budget</ReferencingEntityName>
    <ReferencedEntityName>msnfp_deliveryframework</ReferencedEntityName>
    <CascadeAssign>NoCascade</CascadeAssign>
    <CascadeDelete>RemoveLink</CascadeDelete>
    <CascadeReparent>NoCascade</CascadeReparent>
    <CascadeShare>NoCascade</CascadeShare>
    <CascadeUnshare>NoCascade</CascadeUnshare>
    <CascadeRollupView>NoCascade</CascadeRollupView>
    <IsValidForAdvancedFind>1</IsValidForAdvancedFind>
    <ReferencingAttributeName>msnfp_deliveryframeworkid</ReferencingAttributeName>
    <RelationshipDescription>
      <Descriptions>
        <Description description="" languagecode="1033" />
      </Descriptions>
    </RelationshipDescription>
    <EntityRelationshipRoles>
      <EntityRelationshipRole>
        <NavPaneDisplayOption>UseCollectionName</NavPaneDisplayOption>
        <NavPaneArea>Details</NavPaneArea>
        <NavPaneOrder>10000</NavPaneOrder>
        <NavigationPropertyName>msnfp_deliveryframeworkid</NavigationPropertyName>
        <CustomLabels>
          <CustomLabel description="" languagecode="1033" />
        </CustomLabels>
        <RelationshipRoleType>1</RelationshipRoleType>
      </EntityRelationshipRole>
      <EntityRelationshipRole>
        <RelationshipRoleType>0</RelationshipRoleType>
      </EntityRelationshipRole>
    </EntityRelationshipRoles>
  </EntityRelationship>
  <EntityRelationship Name="msnfp_deliveryframework_deliveryframework_ParentDeliveryFrameworkId">
    <EntityRelationshipType>OneToMany</EntityRelationshipType>
    <IntroducedVersion>1.0.10</IntroducedVersion>
    <IsHierarchical>0</IsHierarchical>
    <ReferencingEntityName>msnfp_deliveryframework</ReferencingEntityName>
    <ReferencedEntityName>msnfp_deliveryframework</ReferencedEntityName>
    <CascadeAssign>NoCascade</CascadeAssign>
    <CascadeDelete>RemoveLink</CascadeDelete>
    <CascadeReparent>NoCascade</CascadeReparent>
    <CascadeShare>NoCascade</CascadeShare>
    <CascadeUnshare>NoCascade</CascadeUnshare>
    <CascadeRollupView>NoCascade</CascadeRollupView>
    <IsValidForAdvancedFind>1</IsValidForAdvancedFind>
    <ReferencingAttributeName>msnfp_ParentDeliveryFrameworkId</ReferencingAttributeName>
    <RelationshipDescription>
      <Descriptions>
        <Description description="Parent DeliveryFramework" languagecode="1033" />
      </Descriptions>
    </RelationshipDescription>
    <EntityRelationshipRoles>
      <EntityRelationshipRole>
        <NavPaneDisplayOption>UseCollectionName</NavPaneDisplayOption>
        <NavPaneArea>Details</NavPaneArea>
        <NavPaneOrder>10000</NavPaneOrder>
        <NavigationPropertyName>msnfp_ParentDeliveryFrameworkId</NavigationPropertyName>
        <CustomLabels>
          <CustomLabel description="" languagecode="1033" />
        </CustomLabels>
        <RelationshipRoleType>1</RelationshipRoleType>
      </EntityRelationshipRole>
      <EntityRelationshipRole>
        <RelationshipRoleType>0</RelationshipRoleType>
      </EntityRelationshipRole>
    </EntityRelationshipRoles>
  </EntityRelationship>
  <EntityRelationship Name="msnfp_deliveryframework_disbursementdistribution_DeliveryFrameworkId">
    <EntityRelationshipType>OneToMany</EntityRelationshipType>
    <IntroducedVersion>1.0.10</IntroducedVersion>
    <IsHierarchical>0</IsHierarchical>
    <ReferencingEntityName>msnfp_disbursementdistribution</ReferencingEntityName>
    <ReferencedEntityName>msnfp_deliveryframework</ReferencedEntityName>
    <CascadeAssign>NoCascade</CascadeAssign>
    <CascadeDelete>RemoveLink</CascadeDelete>
    <CascadeReparent>NoCascade</CascadeReparent>
    <CascadeShare>NoCascade</CascadeShare>
    <CascadeUnshare>NoCascade</CascadeUnshare>
    <CascadeRollupView>NoCascade</CascadeRollupView>
    <IsValidForAdvancedFind>1</IsValidForAdvancedFind>
    <ReferencingAttributeName>msnfp_DeliveryFrameworkId</ReferencingAttributeName>
    <RelationshipDescription>
      <Descriptions>
        <Description description="Delivery Framework" languagecode="1033" />
      </Descriptions>
    </RelationshipDescription>
    <EntityRelationshipRoles>
      <EntityRelationshipRole>
        <NavPaneDisplayOption>UseCollectionName</NavPaneDisplayOption>
        <NavPaneArea>Details</NavPaneArea>
        <NavPaneOrder>10000</NavPaneOrder>
        <NavigationPropertyName>msnfp_DeliveryFrameworkId</NavigationPropertyName>
        <CustomLabels>
          <CustomLabel description="" languagecode="1033" />
        </CustomLabels>
        <RelationshipRoleType>1</RelationshipRoleType>
      </EntityRelationshipRole>
      <EntityRelationshipRole>
        <RelationshipRoleType>0</RelationshipRoleType>
      </EntityRelationshipRole>
    </EntityRelationshipRoles>
  </EntityRelationship>
  <EntityRelationship Name="msnfp_deliveryframework_result_deliveryframeworkid">
    <EntityRelationshipType>OneToMany</EntityRelationshipType>
    <IntroducedVersion>1.0.8</IntroducedVersion>
    <IsHierarchical>0</IsHierarchical>
    <ReferencingEntityName>msnfp_result</ReferencingEntityName>
    <ReferencedEntityName>msnfp_deliveryframework</ReferencedEntityName>
    <CascadeAssign>NoCascade</CascadeAssign>
    <CascadeDelete>RemoveLink</CascadeDelete>
    <CascadeReparent>NoCascade</CascadeReparent>
    <CascadeShare>NoCascade</CascadeShare>
    <CascadeUnshare>NoCascade</CascadeUnshare>
    <CascadeRollupView>NoCascade</CascadeRollupView>
    <IsValidForAdvancedFind>1</IsValidForAdvancedFind>
    <ReferencingAttributeName>msnfp_deliveryframeworkid</ReferencingAttributeName>
    <RelationshipDescription>
      <Descriptions>
        <Description description="" languagecode="1033" />
      </Descriptions>
    </RelationshipDescription>
    <EntityRelationshipRoles>
      <EntityRelationshipRole>
        <NavPaneDisplayOption>UseCollectionName</NavPaneDisplayOption>
        <NavPaneArea>Details</NavPaneArea>
        <NavPaneOrder>10000</NavPaneOrder>
        <NavigationPropertyName>msnfp_deliveryframeworkid</NavigationPropertyName>
        <CustomLabels>
          <CustomLabel description="" languagecode="1033" />
        </CustomLabels>
        <RelationshipRoleType>1</RelationshipRoleType>
      </EntityRelationshipRole>
      <EntityRelationshipRole>
        <RelationshipRoleType>0</RelationshipRoleType>
      </EntityRelationshipRole>
    </EntityRelationshipRoles>
  </EntityRelationship>
</EntityRelationships>