<?xml version="1.0" encoding="utf-8"?>
<optionset Name="msnfp_address" localizedName="Address Timezone" xmlns:xsi="http://www.w3.org/2001/XMLSchema-instance">
  <OptionSetType>picklist</OptionSetType>
  <IsGlobal>1</IsGlobal>
  <IntroducedVersion>2.4.2.4</IntroducedVersion>
  <IsCustomizable>1</IsCustomizable>
  <ExternalTypeName></ExternalTypeName>
  <displaynames>
    <displayname description="Address Timezone" languagecode="1033" />
  </displaynames>
  <Descriptions>
    <Description description="" languagecode="1033" />
  </Descriptions>
  <options>
    <option value="844060000" ExternalValue="" Color="#0000ff">
      <labels>
        <label description="Timezone 1" languagecode="1033" />
      </labels>
      <Descriptions>
        <Description description="" languagecode="1033" />
      </Descriptions>
    </option>
    <option value="844060001" ExternalValue="" Color="#0000ff">
      <labels>
        <label description="Timezone 2" languagecode="1033" />
      </labels>
      <Descriptions>
        <Description description="" languagecode="1033" />
      </Descriptions>
    </option>
    <option value="844060002" ExternalValue="" Color="#0000ff">
      <labels>
        <label description="Timezone 3" languagecode="1033" />
      </labels>
      <Descriptions>
        <Description description="" languagecode="1033" />
      </Descriptions>
    </option>
  </options>
</optionset>